connexion_code_generator/__about__.py
connexion_code_generator/__init__.py
connexion_code_generator/py.typed
connexion_code_generator/cmd/__init__.py
connexion_code_generator/cmd/generate.py
connexion_code_generator/generator/__init__.py
connexion_code_generator/generator/class_template.py.jinja
connexion_code_generator/generator/entities.py
connexion_code_generator/generator/exceptions.py
connexion_code_generator/generator/generator.py
connexion_code_generator/parser/__init__.py
connexion_code_generator/parser/entities.py
connexion_code_generator/parser/enums.py
connexion_code_generator/pkg/__init__.py
connexion_code_generator/pkg/cli/__init__.py
connexion_code_generator/pkg/cli/command.py
connexion_code_generator/pkg/exception/__init__.py
connexion_code_generator/pkg/exception/exception_helper.py
connexion_code_generator-0.0.1.dist-info/METADATA
connexion_code_generator-0.0.1.dist-info/WHEEL
connexion_code_generator-0.0.1.dist-info/entry_points.txt
connexion_code_generator-0.0.1.dist-info/licenses/LICENSE.txt
connexion_code_generator-0.0.1.dist-info/RECORD
