Metadata-Version: 2.1
Name: connexion-code-generator
Version: 0.0.1
Summary: A CLI tool that generates Protocol or Abstract Classes based on your OpenAPI specification.
Project-URL: Documentation, https://github.com/mmohaveri/connexion-code-generator#readme
Project-URL: Issues, https://github.com/mmohaveri/connexion-code-generator/issues
Project-URL: Source, https://github.com/mmohaveri/connexion-code-generator
Author-email: Mahdi Mohaveri <mmohaveri@gmail.com>
License-Expression: MIT
License-File: LICENSE.txt
Keywords: connexion
Classifier: Development Status :: 4 - Beta
Classifier: Environment :: Console
Classifier: Intended Audience :: Developers
Classifier: License :: OSI Approved :: MIT License
Classifier: Operating System :: OS Independent
Classifier: Programming Language :: Python
Classifier: Programming Language :: Python :: 3 :: Only
Classifier: Programming Language :: Python :: 3.10
Classifier: Programming Language :: Python :: 3.11
Classifier: Programming Language :: Python :: Implementation :: CPython
Classifier: Programming Language :: Python :: Implementation :: PyPy
Classifier: Topic :: Software Development :: Code Generators
Classifier: Typing :: Typed
Requires-Python: >=3.10
Requires-Dist: autopep8
Requires-Dist: click
Requires-Dist: jinja2
Requires-Dist: pydantic[email]
Requires-Dist: pyyaml
Requires-Dist: result
